typer_repyt/__init__.py
typer_repyt/build_command.py
typer_repyt/constants.py
typer_repyt/env.py
typer_repyt/exceptions.py
typer_repyt/py.typed
typer_repyt/version.py
typer_repyt_demo/__init__.py
typer_repyt_demo/build_command.py
typer_repyt_demo/helpers.py
typer_repyt_demo/main.py
typer_repyt-0.8.1.dist-info/METADATA
typer_repyt-0.8.1.dist-info/WHEEL
typer_repyt-0.8.1.dist-info/entry_points.txt
typer_repyt-0.8.1.dist-info/licenses/LICENSE.md
typer_repyt-0.8.1.dist-info/RECORD
