Metadata-Version: 2.4
Name: typer-repyt
Version: 0.8.1
Summary: Build Typer commands dynamically
Project-URL: homepage, https://github.com/dusktreader/typer-repyt
Project-URL: source, https://github.com/dusktreader/typer-repyt
Project-URL: changelog, https://github.com/dusktreader/typer-repyt/blob/main/CHANGELOG.md
Author-email: Tucker Beck <tucker.beck@gmail.com>
License-File: LICENSE.md
Requires-Python: <3.15,>=3.12
Requires-Dist: humanize>=4.12.2
Requires-Dist: inflection>=0.5.1
Requires-Dist: py-buzz~=7.3
Requires-Dist: pydantic>=2.11.3
Requires-Dist: snick~=2.1
Requires-Dist: typer>=0.15.2
Provides-Extra: demo
Requires-Dist: auto-name-enum>=3.0.0; extra == 'demo'
Requires-Dist: rich>=14.0.0; extra == 'demo'
